crlibm.cp35-win32.pyd
crlibm-1.0.3.dist-info/DESCRIPTION.rst
crlibm-1.0.3.dist-info/METADATA
crlibm-1.0.3.dist-info/RECORD
crlibm-1.0.3.dist-info/WHEEL
crlibm-1.0.3.dist-info/metadata.json
crlibm-1.0.3.dist-info/top_level.txt
