Metadata-Version: 2.0
Name: crlibm
Version: 1.0.3
Summary: Python bindings for CRlibm, an efficient and proven correctly-rounded mathematical library
Home-page: https://github.com/taschini/pycrlibm
Author: Stefano Taschini
Author-email: taschini@gmail.com
License: LGPLv2+
Keywords: crlibm
Platform: 
Classifier: Development Status :: 5 - Production/Stable
Classifier: License :: OSI Approved :: GNU Lesser General Public License v2 or later (LGPLv2+)
Classifier: Operating System :: MacOS :: MacOS X
Classifier: Operating System :: Microsoft :: Windows
Classifier: Operating System :: POSIX :: Linux
Classifier: Programming Language :: C
Classifier: Programming Language :: Python
Classifier: Programming Language :: Python :: 2
Classifier: Programming Language :: Python :: 2.6
Classifier: Programming Language :: Python :: 2.7
Classifier: Programming Language :: Python :: 3
Classifier: Programming Language :: Python :: 3.5
Classifier: Programming Language :: Python :: Implementation :: CPython
Classifier: Topic :: Scientific/Engineering :: Mathematics
Provides-Extra: develop
Requires-Dist: Sphinx; extra == 'develop'
Requires-Dist: flake8; extra == 'develop'
Requires-Dist: tox; extra == 'develop'
Requires-Dist: zest.releaser[recommended]; extra == 'develop'
